MANIFEST.in
README.rst
setup.py
djangocms_reversion2/__init__.py
djangocms_reversion2/admin.py
djangocms_reversion2/apps.py
djangocms_reversion2/cms_toolbars.py
djangocms_reversion2/diff.py
djangocms_reversion2/exporter.py
djangocms_reversion2/forms.py
djangocms_reversion2/models.py
djangocms_reversion2/page_revisions.py
djangocms_reversion2/setup.py
djangocms_reversion2/signals.py
djangocms_reversion2/trash.py
djangocms_reversion2/utils.py
djangocms_reversion2/views.py
djangocms_reversion2.egg-info/PKG-INFO
djangocms_reversion2.egg-info/SOURCES.txt
djangocms_reversion2.egg-info/dependency_links.txt
djangocms_reversion2.egg-info/requires.txt
djangocms_reversion2.egg-info/top_level.txt
djangocms_reversion2/migrations/0001_initial.py
djangocms_reversion2/migrations/0002_pageversion_language.py
djangocms_reversion2/migrations/0003_pageversion_dirty.py
djangocms_reversion2/migrations/0004_auto_20170526_1128.py
djangocms_reversion2/migrations/__init__.py
djangocms_reversion2/templates/admin/audit_trail.html
djangocms_reversion2/templates/admin/bin_menu.html
djangocms_reversion2/templates/admin/close_frame.html
djangocms_reversion2/templates/admin/diff.html
djangocms_reversion2/templates/admin/diff_old.html
djangocms_reversion2/templates/admin/download_audit_trail.html
djangocms_reversion2/templates/admin/view_revision.html
test_app/configuration/__init__.py
test_app/configuration/settings.py
test_app/configuration/urls.py
test_app/configuration/wsgi.py
test_app/tests/__init__.py
test_app/tests/tests.py
test_app/tests/testutils.py